prismalog/__init__.py
prismalog/argparser.py
prismalog/config.py
prismalog/log.py
prismalog/py.typed
prismalog-0.1.3.dist-info/licenses/LICENSE
prismalog-0.1.3.dist-info/METADATA
prismalog-0.1.3.dist-info/WHEEL
prismalog-0.1.3.dist-info/top_level.txt
prismalog-0.1.3.dist-info/RECORD
