Metadata-Version: 2.4
Name: prismalog
Version: 0.1.3
Summary: High-performance colored, multi-process logging library for Python
Author-email: Alexey Obukhov <alexey.obukhov@hotmail.com>
License: MIT
Project-URL: Homepage, https://github.com/vertok/prismalog
Project-URL: Documentation, https://prismalog.readthedocs.io/
Project-URL: Issues, https://github.com/vertok/prismalog/issues
Project-URL: Changelog, https://github.com/vertok/prismalog/blob/main/CHANGELOG.md
Keywords: logging,colored,high-performance,multiprocessing
Classifier: Programming Language :: Python :: 3
Classifier: Programming Language :: Python :: 3.8
Classifier: Programming Language :: Python :: 3.10
Classifier: Programming Language :: Python :: 3.11
Classifier: License :: OSI Approved :: MIT License
Classifier: Operating System :: OS Independent
Classifier: Topic :: System :: Logging
Requires-Python: >=3.8
License-File: LICENSE
Provides-Extra: yaml
Requires-Dist: PyYAML>=6.0.1; extra == "yaml"
Provides-Extra: dev
Requires-Dist: black>=22.6.0; extra == "dev"
Requires-Dist: pylint>=2.14.0; extra == "dev"
Requires-Dist: mypy>=1.0.0; extra == "dev"
Requires-Dist: isort>=5.10.0; extra == "dev"
Requires-Dist: build>=0.8.0; extra == "dev"
Requires-Dist: twine>=4.0.0; extra == "dev"
Requires-Dist: flake8>=5.0.0; extra == "dev"
Requires-Dist: pre-commit>=3.5.0; extra == "dev"
Requires-Dist: PyYAML>=6.0.2; extra == "dev"
Provides-Extra: test
Requires-Dist: pytest>=8.3.5; extra == "test"
Requires-Dist: pytest-cov>=3.0.0; extra == "test"
Requires-Dist: pytest-html>=3.2.0; extra == "test"
Requires-Dist: pytest-timeout>=2.1.0; extra == "test"
Requires-Dist: coverage>=7.6.1; extra == "test"
Requires-Dist: nltk>=3.9.1; extra == "test"
Requires-Dist: PyYAML>=6.0.2; extra == "test"
Provides-Extra: doc
Requires-Dist: sphinx>=4.5.0; extra == "doc"
Requires-Dist: sphinx-rtd-theme>=1.0.0; extra == "doc"
Requires-Dist: sphinx-autodoc-typehints>=1.18.0; extra == "doc"
Requires-Dist: sphinx-design>=0.5.0; extra == "doc"
Provides-Extra: ci
Requires-Dist: anybadge>=1.10.0; extra == "ci"
Provides-Extra: all
Requires-Dist: black>=22.6.0; extra == "all"
Requires-Dist: pylint>=2.14.0; extra == "all"
Requires-Dist: mypy>=1.0.0; extra == "all"
Requires-Dist: isort>=5.10.0; extra == "all"
Requires-Dist: build>=0.8.0; extra == "all"
Requires-Dist: twine>=4.0.0; extra == "all"
Requires-Dist: flake8>=5.0.0; extra == "all"
Requires-Dist: pre-commit>=3.5.0; extra == "all"
Requires-Dist: PyYAML>=6.0.2; extra == "all"
Requires-Dist: pytest>=8.3.5; extra == "all"
Requires-Dist: pytest-cov>=3.0.0; extra == "all"
Requires-Dist: pytest-html>=3.2.0; extra == "all"
Requires-Dist: pytest-timeout>=2.1.0; extra == "all"
Requires-Dist: coverage>=7.6.1; extra == "all"
Requires-Dist: nltk>=3.9.1; extra == "all"
Requires-Dist: sphinx>=4.5.0; extra == "all"
Requires-Dist: sphinx-rtd-theme>=1.0.0; extra == "all"
Requires-Dist: sphinx-autodoc-typehints>=1.18.0; extra == "all"
Requires-Dist: sphinx-design>=0.5.0; extra == "all"
Requires-Dist: anybadge>=1.10.0; extra == "all"
Dynamic: license-file
